{
  "cli": {
    "version": ">= 12.0.0",
    "appVersionSource": "remote"
  },
  "build": {
    "development": {
      "developmentClient": true,
      "distribution": "internal",
      "env": {
        "EXPO_PUBLIC_ENVIRONMENT": "development",
        "EXPO_PUBLIC_AUTH0_DOMAIN": "dev-dv5sxg3q0hnih5mb.us.auth0.com",
        "EXPO_PUBLIC_AUTH0_CLIENT_ID": "oIO2Q226dOaueczzCSjfSMYkbl3jbF2G",
        "EXPO_PUBLIC_AUTH0_AUDIENCE": "https://hue2-production.up.railway.app/mcp/"
      }
    },
    "staging": {
      "distribution": "internal",
      "env": {
        "EXPO_PUBLIC_ENVIRONMENT": "staging",
        "EXPO_PUBLIC_AUTH0_DOMAIN": "dev-dv5sxg3q0hnih5mb.us.auth0.com",
        "EXPO_PUBLIC_AUTH0_CLIENT_ID": "oIO2Q226dOaueczzCSjfSMYkbl3jbF2G",
        "EXPO_PUBLIC_AUTH0_AUDIENCE": "https://hue2-production.up.railway.app/mcp/"
      }
    },
    "production": {
      "distribution": "internal",
      "autoIncrement": true,
      "env": {
        "EXPO_PUBLIC_ENVIRONMENT": "production",
        "EXPO_PUBLIC_API_URL_PRODUCTION": "https://hue2-production.up.railway.app",
        "EXPO_PUBLIC_AUTH0_DOMAIN": "dev-dv5sxg3q0hnih5mb.us.auth0.com",
        "EXPO_PUBLIC_AUTH0_CLIENT_ID": "oIO2Q226dOaueczzCSjfSMYkbl3jbF2G",
        "EXPO_PUBLIC_AUTH0_AUDIENCE": "https://hue2-production.up.railway.app/mcp/"
      }
    },
    "app-store": {
      "distribution": "store",
      "autoIncrement": true,
      "env": {
        "EXPO_PUBLIC_ENVIRONMENT": "production",
        "EXPO_PUBLIC_API_URL_PRODUCTION": "https://hue2-production.up.railway.app",
        "EXPO_PUBLIC_AUTH0_DOMAIN": "dev-dv5sxg3q0hnih5mb.us.auth0.com",
        "EXPO_PUBLIC_AUTH0_CLIENT_ID": "oIO2Q226dOaueczzCSjfSMYkbl3jbF2G",
        "EXPO_PUBLIC_AUTH0_AUDIENCE": "https://hue2-production.up.railway.app/mcp/"
      }
    }
  },
  "submit": {
    "app-store": {}
  }
}
